congressy/__init__.py
congressy/configurations.py
congressy/constants.py
congressy/exceptions.py
congressy/http.py
congressy/attendance/__init__.py
congressy/core/__init__.py
congressy/core/models/__init__.py
congressy/core/models/fields.py
congressy/core/models/model.py
congressy/core/synchable_models/__init__.py
congressy/core/synchable_models/feature.py
congressy/core/synchable_models/synchable_managers.py
congressy/core/synchable_models/synchable_models.py
congressy/integrations/__init__.py
congressy/integrations/mailchimp.py
congressy/videos/__init__.py
congressy/videos/category.py
congressy/videos/namespace.py
congressy/videos/playlist.py
congressy/videos/project.py
congressy/videos/subscriber.py
congressy/videos/user.py
congressy/videos/video.py
tests/__init__.py
tests/core/__init__.py
tests/core/http/__init__.py
tests/core/http/test_resource.py
tests/core/http/test_transporter.py
tests/core/models/__init__.py
tests/core/models/test_fields.py
tests/core/models/test_model.py
tests/core/synchable_models/__init__.py
tests/core/synchable_models/test_synchable_managers.py
tests/core/synchable_models/test_synchable_models.py
congressy_sdk-0.0.4.dist-info/LICENSE
congressy_sdk-0.0.4.dist-info/METADATA
congressy_sdk-0.0.4.dist-info/WHEEL
congressy_sdk-0.0.4.dist-info/top_level.txt
congressy_sdk-0.0.4.dist-info/RECORD
