Metadata-Version: 2.1
Name: congressy-sdk
Version: 0.0.4
Summary: A python client for v1 of Congressy API
Home-page: https://bitbucket.org/congressy/congressy-sdk-python
Author: Hugo Seabra
Author-email: infra@congressy.com
License: MIT
Keywords: congressy api v1 client wrapper event platform
Platform: UNKNOWN
Classifier: Development Status :: 5 - Production/Stable
Classifier: Intended Audience :: Developers
Classifier: Topic :: Software Development :: Libraries :: Python Modules
Classifier: License :: OSI Approved :: MIT License
Classifier: Programming Language :: Python :: 3.5
Classifier: Programming Language :: Python :: 3.6
Classifier: Programming Language :: Python :: 3.7
Classifier: Operating System :: OS Independent
Requires-Python: >=3.5
Requires-Dist: requests (<=2.22.0,>=2.18.2)
Requires-Dist: requests[security]
Requires-Dist: validation (==0.5.0)
Requires-Dist: pytz (==2019.3)
